Orange3_Geo_Fork-0.3.3-py3.6-nspkg.pth
orangecontrib/geof/HRangeSlider.py
orangecontrib/geof/__init__.py
orangecontrib/geof/_test.py
orangecontrib/geof/cc_cities.py
orangecontrib/geof/mapper.py
orangecontrib/geof/utils.py
orangecontrib/geof/worldcities.csv
orangecontrib/geof/datasets/HDI-small.csv
orangecontrib/geof/datasets/India_census_district_population.csv
orangecontrib/geof/geojson/admin0.json
orangecontrib/geof/geojson/admin1-ABW.json
orangecontrib/geof/geojson/admin1-AFG.json
orangecontrib/geof/geojson/admin1-AGO.json
orangecontrib/geof/geojson/admin1-AIA.json
orangecontrib/geof/geojson/admin1-ALB.json
orangecontrib/geof/geojson/admin1-ALD.json
orangecontrib/geof/geojson/admin1-AND.json
orangecontrib/geof/geojson/admin1-ARE.json
orangecontrib/geof/geojson/admin1-ARG.json
orangecontrib/geof/geojson/admin1-ARM.json
orangecontrib/geof/geojson/admin1-ASM.json
orangecontrib/geof/geojson/admin1-ATA.json
orangecontrib/geof/geojson/admin1-ATC.json
orangecontrib/geof/geojson/admin1-ATF.json
orangecontrib/geof/geojson/admin1-ATG.json
orangecontrib/geof/geojson/admin1-AUS.json
orangecontrib/geof/geojson/admin1-AUT.json
orangecontrib/geof/geojson/admin1-AZE.json
orangecontrib/geof/geojson/admin1-BDI.json
orangecontrib/geof/geojson/admin1-BEL.json
orangecontrib/geof/geojson/admin1-BEN.json
orangecontrib/geof/geojson/admin1-BFA.json
orangecontrib/geof/geojson/admin1-BGD.json
orangecontrib/geof/geojson/admin1-BGR.json
orangecontrib/geof/geojson/admin1-BHR.json
orangecontrib/geof/geojson/admin1-BHS.json
orangecontrib/geof/geojson/admin1-BIH.json
orangecontrib/geof/geojson/admin1-BLM.json
orangecontrib/geof/geojson/admin1-BLR.json
orangecontrib/geof/geojson/admin1-BLZ.json
orangecontrib/geof/geojson/admin1-BMU.json
orangecontrib/geof/geojson/admin1-BOL.json
orangecontrib/geof/geojson/admin1-BRA.json
orangecontrib/geof/geojson/admin1-BRB.json
orangecontrib/geof/geojson/admin1-BRN.json
orangecontrib/geof/geojson/admin1-BTN.json
orangecontrib/geof/geojson/admin1-BWA.json
Orange3_Geo_Fork-0.3.3.dist-info/COPYING.txt
Orange3_Geo_Fork-0.3.3.dist-info/METADATA
Orange3_Geo_Fork-0.3.3.dist-info/WHEEL
Orange3_Geo_Fork-0.3.3.dist-info/entry_points.txt
Orange3_Geo_Fork-0.3.3.dist-info/namespace_packages.txt
Orange3_Geo_Fork-0.3.3.dist-info/top_level.txt
Orange3_Geo_Fork-0.3.3.dist-info/RECORD
